volcengine/ApiInfo.py
volcengine/Credentials.py
volcengine/Policy.py
volcengine/ServiceInfo.py
volcengine/__init__.py
volcengine/adblocker/AdBlockerService.py
volcengine/adblocker/__init__.py
volcengine/auth/MetaData.py
volcengine/auth/SignParam.py
volcengine/auth/SignResult.py
volcengine/auth/SignerV4.py
volcengine/auth/__init__.py
volcengine/base/Request.py
volcengine/base/Service.py
volcengine/base/__init__.py
volcengine/base/models/__init__.py
volcengine/base/models/base/__init__.py
volcengine/base/models/base/base_pb2.py
volcengine/billing/BillingService.py
volcengine/billing/__init__.py
volcengine/business_security/RiskDetectionService.py
volcengine/business_security/__init__.py
volcengine/cdn/__init__.py
volcengine/cdn/service.py
volcengine/code_pipeline/CodePipelineService.py
volcengine/code_pipeline/__init__.py
volcengine/const/Const.py
volcengine/const/__init__.py
volcengine/content_security/ContentSecurityService.py
volcengine/content_security/__init__.py
volcengine/example/DemoSignOnly.py
volcengine/example/__init__.py
volcengine/example/cdn/__init__.py
volcengine/example/cdn/add_cdn_certificate.py
volcengine/example/cdn/add_cdn_domain.py
volcengine/example/cdn/add_resource_tags.py
volcengine/example/cdn/batch_deploy_cert.py
volcengine/example/cdn/delete_cdn_domain.py
volcengine/example/cdn/delete_resource_tags.py
volcengine/example/cdn/describe_accounting_data.py
volcengine/example/cdn/describe_cdn_access_log.py
volcengine/example/cdn/describe_cdn_config.py
volcengine/example/cdn/describe_cdn_data.py
volcengine/example/cdn/describe_cdn_detail.py
volcengine/example/cdn/describe_cdn_domain_top_data.py
volcengine/example/cdn/describe_cdn_origin_data.py
volcengine/example/cdn/describe_cdn_region_and_isp.py
volcengine/example/cdn/describe_cdn_service.py
volcengine/example/cdn/describe_cdn_upper_ip.py
volcengine/example/cdn/describe_cert_config.py
volcengine/example/cdn/describe_content_block_tasks.py
volcengine/example/cdn/describe_content_quota.py
vop_sdk-1.0.0.dist-info/METADATA
vop_sdk-1.0.0.dist-info/WHEEL
vop_sdk-1.0.0.dist-info/top_level.txt
vop_sdk-1.0.0.dist-info/RECORD
