Metadata-Version: 2.1
Name: vop-sdk
Version: 1.0.0
Summary: The Vop SDK for Python
Home-page: https://github.com/Volcengine/volc-sdk-python
Author: Vop SDK
Author-email: liangqing.leon@bytedance.com
License: MIT Licence
Keywords: pip,vop,vop-sdk-python
Platform: any
Requires-Dist: requests
Requires-Dist: retry
Requires-Dist: pytz
Requires-Dist: pycryptodome
Requires-Dist: protobuf
Requires-Dist: google
Requires-Dist: six
Requires-Dist: lz4a
